{
	"name":"문의 게시판",
	"total":9,
	"item":[
		{
			"no":9,
			"title":"<a href = '#'>세종 소극장 음료 반입 되나요?</a>",
			"user":"김시원",
			"date":"2020.01.09",
			"response":""
		},
		{
			"no":8,
			"title":"<a href = '#'>여자만세2 좌석 변경 하려고하는데..</a>",
			"user":"방희은",
			"date":"2020.01.08",
			"response":"답변완료"
		},
		{
			"no":"",
			"title":"<a href = '#'>┖> [예술의 전당입니다.]</a>",
			"user":"관리자",
			"date":"2020.01.09",
			"response":""
		},
		
		{
			"no":7,
			"title":"<a href = '#'>2020 밀레니엄 신년 음악회 몇시간정도 하나요?",
			"user":"김제주",
			"date":"2020.01.08",
			"response":"답변완료"
		},
		{
			"no":"",
			"title":"<a href = '#'>┖> [예술의 전당입니다.]</a>",
			"user":"관리자",
			"date":"2020.01.08",
			"response":""
		},
		{
			"no":6,
			"title":"<a href = '#'>뮤지컬 오페라티 공연 언제까지 하나요??</a>",
			"user":"쵀태식",
			"date":"2020.01.07",
			"response":"답변완료"
		},
		{
			"no":"",
			"title":"<a href = '#'>┖> [예술의 전당입니다.]</a>",
			"user":"관리자",
			"date":"2020.01.09",
			"response":""
		},
		{
			"no":5,
			"title":"<a href = '#'>백조와 호수 표 환불 신청했는데 언제쯤 처리되나요??</a>",
			"user":"박스완",
			"date":"2020.01.04",
			"response":""
		},
		
		{
			"no":4,
			"title":"<a href = '#'>오페라 엘리압 예약 언제부터 가능하나요?</a>",
			"user":"이민정",
			"date":"2020.01.02",
			"response":""
		
		},
		{
			"no":3,
			"title":"<a href = '#'>뮤지컬 캣츠 공연 일정이 어떻게 되죠??</a>",
			"user":"김에스더",
			"date":"2019.12.28",
			"response":"답변완료"

		},
		{
			"no":"",
			"title":"<a href = '#'>┖> [예술의 전당입니다.]</a>",
			"user":"관리자",
			"date":"2019.12.30",
			"response":""
		},
		{
			"no":2,
			"title":"<a href = '#'>연극 옥탑방 고양이 예약하고 싶은데 어떻게 하면 되죠??</a>",
			"user":"반려묘",
			"date":"2019.12.16",
			"response":"답변완료"
		
		},
		{
			"no":"",
			"title":"<a href = '#'>┖> [예술의 전당입니다.]</a>",
			"user":"관리자",
			"date":"2019.12.19",
			"response":""
		},
		{
			"no":1,
			"title":"<a href = '#'>지킬 앤 하이드 시사회 날짜 언제쯤 나오나요??</a>",
			"user":"김민수",
			"date":"2019.11.26",
			"response":"답변완료"

		},
		{
			"no":"",
			"title":"<a href = '#'>┖> [예술의 전당입니다.]</a>",
			"user":"관리자",
			"date":"2019.11.27",
			"response":""
		}
	]
}